pythonfmu/__init__.py
pythonfmu/__main__.py
pythonfmu/_version.py
pythonfmu/builder.py
pythonfmu/csvbuilder.py
pythonfmu/default_experiment.py
pythonfmu/deploy.py
pythonfmu/enums.py
pythonfmu/fmi2slave.py
pythonfmu/logmsg.py
pythonfmu/osutil.py
pythonfmu/variables.py
pythonfmu/pythonfmu-export/.clang-format
pythonfmu/pythonfmu-export/CMakeLists.txt
pythonfmu/pythonfmu-export/build_unix.sh
pythonfmu/pythonfmu-export/build_win.sh
pythonfmu/pythonfmu-export/src/CMakeLists.txt
pythonfmu/pythonfmu-export/src/fmi/fmi2FunctionTypes.h
pythonfmu/pythonfmu-export/src/fmi/fmi2Functions.h
pythonfmu/pythonfmu-export/src/fmi/fmi2TypesPlatform.h
pythonfmu/pythonfmu-export/src/pythonfmu/IPyState.hpp
pythonfmu/pythonfmu-export/src/pythonfmu/Logger.hpp
pythonfmu/pythonfmu-export/src/pythonfmu/PySlaveInstance.cpp
pythonfmu/pythonfmu-export/src/pythonfmu/PyState.hpp
pythonfmu/pythonfmu-export/src/pythonfmu/SlaveInstance.hpp
pythonfmu/pythonfmu-export/src/pythonfmu/fmi2.cpp
pythonfmu/pythonfmu-export/src/pythonfmu/fmu_except.hpp
pythonfmu/resources/binaries/linux64/libpythonfmu-export.so
pythonfmu/resources/binaries/win64/pythonfmu-export.dll
pythonfmu/tests/__init__.py
pythonfmu/tests/test_builder.py
pythonfmu/tests/test_csvslave.py
pythonfmu/tests/test_default_experiment.py
pythonfmu/tests/test_deploy.py
pythonfmu/tests/test_fmi2slave.py
pythonfmu/tests/test_integration.py
pythonfmu/tests/test_logger.py
pythonfmu/tests/test_multiple_fmus.py
pythonfmu/tests/test_variables.py
pythonfmu/tests/utils.py
pythonfmu/tests/data/csvdemo.csv
pythonfmu/tests/data/hello.txt
pythonfmu/tests/slaves/PythonSlaveWithException.py
pythonfmu/tests/slaves/localmodule.py
pythonfmu/tests/slaves/pythonslave.py
pythonfmu/tests/slaves/pythonslave_default_ex.py
pythonfmu/tests/slaves/pythonslave_read_file.py
pythonfmu/tests/slaves/slavewithdep.py
pythonfmu-0.6.9.dist-info/licenses/LICENSE
pythonfmu-0.6.9.dist-info/METADATA
pythonfmu-0.6.9.dist-info/WHEEL
pythonfmu-0.6.9.dist-info/entry_points.txt
pythonfmu-0.6.9.dist-info/top_level.txt
pythonfmu-0.6.9.dist-info/RECORD
